vastai/__init__.py
vastai/serverless/__init__.py
vastai/serverless/client/__init__.py
vastai/serverless/client/client.py
vastai/serverless/client/connection.py
vastai/serverless/client/endpoint.py
vastai/serverless/client/worker.py
vastai/serverless/server/__init__.py
vastai/serverless/server/lib/__init__.py
vastai/serverless/server/lib/backend.py
vastai/serverless/server/lib/data_types.py
vastai/serverless/server/lib/metrics.py
vastai/serverless/server/lib/server.py
vastai/serverless/server/worker.py
vastai/vast.py
vastai/vastai_base.py
vastai/vastai_sdk.py
vastai_sdk/__init__.py
vastai_sdk-0.3.1.dist-info/METADATA
vastai_sdk-0.3.1.dist-info/WHEEL
vastai_sdk-0.3.1.dist-info/licenses/LICENSE
vastai_sdk-0.3.1.dist-info/RECORD
