Metadata-Version: 2.4
Name: vastai-sdk
Version: 0.3.1
Summary: SDK for Vast.ai GPU Cloud Service
License-File: LICENSE
Author: Chris McKenzie
Author-email: chris@vast.ai
Requires-Python: >=3.9
Classifier: Programming Language :: Python :: 3
Classifier: Programming Language :: Python :: 3.9
Classifier: Programming Language :: Python :: 3.10
Classifier: Programming Language :: Python :: 3.11
Classifier: Programming Language :: Python :: 3.12
Classifier: Programming Language :: Python :: 3.13
Classifier: Programming Language :: Python :: 3.14
Requires-Dist: aiodns (>=3.6.0)
Requires-Dist: aiohttp (==3.10.1)
Requires-Dist: anyio (>=4.4,<4.5)
Requires-Dist: borb (>=2.1.25,<2.2.0)
Requires-Dist: fastapi (>=0.110,<1.0)
Requires-Dist: hf_transfer (>=0.1.9)
Requires-Dist: jsonschema (>=3.2)
Requires-Dist: nltk (>=3.9,<3.10)
Requires-Dist: psutil (>=6.0,<6.1)
Requires-Dist: pycares (==4.11.0)
Requires-Dist: pycryptodome (>=3.20,<3.21)
Requires-Dist: pyparsing (>=3.1,<4.0)
Requires-Dist: python-dateutil (>=2.8.2)
Requires-Dist: pytz (>=2023.3)
Requires-Dist: requests (==2.32.3)
Requires-Dist: transformers (>=4.52,<4.53)
Requires-Dist: urllib3 (>=2.0,<3.0)
Requires-Dist: uvicorn[standard] (>=0.24,<0.32)
Requires-Dist: xdg (>=1.0.0)
Project-URL: Homepage, https://vast.ai
Project-URL: Repository, https://github.com/vast-ai/vast-sdk
Project-URL: Source, https://github.com/vast-ai/vast-sdk
